nelo2_logging_handler/__init__.py
nelo2_logging_handler/nelo2_logging_handler.py
nelo2_logging_handler-0.1.12.dist-info/WHEEL
nelo2_logging_handler-0.1.12.dist-info/METADATA
nelo2_logging_handler-0.1.12.dist-info/RECORD
